mambular/__init__.py
mambular/__version__.py
mambular/arch_utils/__init__.py
mambular/arch_utils/cnn_utils.py
mambular/arch_utils/data_aware_initialization.py
mambular/arch_utils/enode_utils.py
mambular/arch_utils/get_norm_fn.py
mambular/arch_utils/layer_utils/__init__.py
mambular/arch_utils/layer_utils/attention_net_arch_utils.py
mambular/arch_utils/layer_utils/attention_utils.py
mambular/arch_utils/layer_utils/batch_ensemble_layer.py
mambular/arch_utils/layer_utils/block_diagonal.py
mambular/arch_utils/layer_utils/embedding_layer.py
mambular/arch_utils/layer_utils/embedding_tree.py
mambular/arch_utils/layer_utils/importance.py
mambular/arch_utils/layer_utils/invariance_layer.py
mambular/arch_utils/layer_utils/normalization_layers.py
mambular/arch_utils/layer_utils/plr_layer.py
mambular/arch_utils/layer_utils/poly_layer.py
mambular/arch_utils/layer_utils/rotary_utils.py
mambular/arch_utils/layer_utils/sn_linear.py
mambular/arch_utils/layer_utils/sparsemax.py
mambular/arch_utils/learnable_ple.py
mambular/arch_utils/lstm_utils.py
mambular/arch_utils/mamba_utils/__init__.py
mambular/arch_utils/mamba_utils/init_weights.py
mambular/arch_utils/mamba_utils/mamba_arch.py
mambular/arch_utils/mamba_utils/mamba_original.py
mambular/arch_utils/mamba_utils/mambattn_arch.py
mambular/arch_utils/mlp_utils.py
mambular/arch_utils/neural_decision_tree.py
mambular/arch_utils/node_utils.py
mambular/arch_utils/numpy_utils.py
mambular/arch_utils/resnet_utils.py
mambular/arch_utils/rnn_utils.py
mambular/arch_utils/simple_utils.py
mambular/arch_utils/transformer_utils.py
mambular/arch_utils/trompt_utils.py
mambular/base_models/__init__.py
mambular/base_models/autoint.py
mambular/base_models/enode.py
mambular/base_models/ft_transformer.py
mambular/base_models/mambatab.py
mambular/base_models/mambattn.py
mambular/base_models/mambular.py
mambular/base_models/mlp.py
mambular/base_models/modern_nca.py
mambular/base_models/ndtf.py
mambular/base_models/node.py
mambular/base_models/resnet.py
mambular-1.5.1.dist-info/LICENSE
mambular-1.5.1.dist-info/METADATA
mambular-1.5.1.dist-info/WHEEL
mambular-1.5.1.dist-info/RECORD
