Metadata-Version: 2.3
Name: mambular
Version: 1.5.1
Summary: A python package for tabular deep learning with mamba blocks.
Author: Anton Thielmann
Requires-Python: >=3.10,<=3.13
Classifier: Programming Language :: Python :: 3
Classifier: Programming Language :: Python :: 3.10
Classifier: Programming Language :: Python :: 3.11
Classifier: Programming Language :: Python :: 3.12
Classifier: Programming Language :: Python :: 3.13
Requires-Dist: accelerate (>=1.2.1,<2.0.0)
Requires-Dist: einops (>=0.8.0,<0.9.0)
Requires-Dist: lightning (>=2.3.3,<3.0.0)
Requires-Dist: numpy (<=1.26.4)
Requires-Dist: pandas (>=2.0.3,<3.0.0)
Requires-Dist: pretab (>=0.0.1,<0.0.2)
Requires-Dist: properscoring (>=0.1,<0.2)
Requires-Dist: scikit-learn (>=1.3.2,<2.0.0)
Requires-Dist: scikit-optimize (>=0.10.2,<0.11.0)
Requires-Dist: scipy (>=1.15.0,<2.0.0)
Requires-Dist: setuptools (>=75.3.0,<76.0.0)
Requires-Dist: torch (>=2.2.2,<=2.7.0)
Requires-Dist: torchmetrics (>=1.5.2,<2.0.0)
Project-URL: documentation, https://mambular.readthedocs.io/en/
Project-URL: homepage, https://github.com/basf/mamba-tabular
Project-URL: package, https://pypi.org/project/mambular/
Project-URL: repository, https://github.com/basf/mamba-tabular
